spatialoperations/__init__.py
geospatial_analysis_environment-0.1.21.dist-info/METADATA
geospatial_analysis_environment-0.1.21.dist-info/WHEEL
geospatial_analysis_environment-0.1.21.dist-info/top_level.txt
geospatial_analysis_environment-0.1.21.dist-info/RECORD
